MANIFEST.in
setup.py
BoutiqueCommons.egg-info/PKG-INFO
BoutiqueCommons.egg-info/SOURCES.txt
BoutiqueCommons.egg-info/dependency_links.txt
BoutiqueCommons.egg-info/not-zip-safe
BoutiqueCommons.egg-info/requires.txt
BoutiqueCommons.egg-info/top_level.txt
boutiquecommons/__init__.py
boutiquecommons/currency.py
boutiquecommons/datetimeutil.py
boutiquecommons/unit_system.py
boutiquecommons/template/__init__.py
boutiquecommons/template/filters.py