Metadata-Version: 1.0
Name: BoutiqueCommons
Version: 0.1.3
Summary: Boutique Commons
Home-page: UNKNOWN
Author: Boutiqueforge
Author-email: hello@boutiqueforge.com
License: UNKNOWN
Platform: UNKNOWN
